{"type":"FeatureCollection","features":[{"type":"Feature","properties":{"marker-color":"#4af434","marker-size":"medium","marker-symbol":"park","Placename":"Quadra West Park","notes":"an obscure triangular park with an amazing view","Contributor":"Sara J"},"geometry":{"type":"Point","coordinates":[-123.18072259426117,49.257086871857844]}}]}